jspyr/__init__.py
jspyr/__main__.py
jspyr/cli.py
jspyr/py.typed
jspyr-0.1.0.dist-info/LICENSE
jspyr-0.1.0.dist-info/METADATA
jspyr-0.1.0.dist-info/WHEEL
jspyr-0.1.0.dist-info/entry_points.txt
jspyr-0.1.0.dist-info/top_level.txt
jspyr-0.1.0.dist-info/RECORD
